{
    "id": "tao",
    "english": "tào",
    "strokes": 10,
    "wordAudio": "audio/words/tao.mp3",
    "importantCharacter":[0],
    "mainGraphics": [
        "images/lesson17/characters/tao.png"
    ],
    "strokeAudio": [
        "audio/strokes/01.mp3",
        "audio/strokes/02.mp3",
        "audio/strokes/03.mp3",
        "audio/strokes/04.mp3",
        "audio/strokes/05.mp3",
        "audio/strokes/06.mp3",
        "audio/strokes/07.mp3",
        "audio/strokes/08.mp3",
        "audio/strokes/09.mp3",
        "audio/strokes/10.mp3"
    ],
    "strokePng": [
        "images/lesson17/tao/tao-01.png",
        "images/lesson17/tao/tao-02.png",
        "images/lesson17/tao/tao-03.png",
        "images/lesson17/tao/tao-04.png",
        "images/lesson17/tao/tao-05.png",
        "images/lesson17/tao/tao-06.png",
        "images/lesson17/tao/tao-07.png",
        "images/lesson17/tao/tao-08.png",
        "images/lesson17/tao/tao-09.png",
        "images/lesson17/tao/tao-10.png"
    ],
    "characterAnimated": "images/character-animated/lesson17/tao.mp4",
    "timecodes": [
        "00:00:00",
        "00:00:02",
        "00:00:04",
        "00:00:06",
        "00:00:08",
        "00:00:10",
        "00:00:12",
        "00:00:14",
        "00:00:16",
        "00:00:18"
    ]
}